listsave.py
listsave-1.2.0.dist-info/DESCRIPTION.rst
listsave-1.2.0.dist-info/METADATA
listsave-1.2.0.dist-info/RECORD
listsave-1.2.0.dist-info/WHEEL
listsave-1.2.0.dist-info/metadata.json
listsave-1.2.0.dist-info/top_level.txt
