Metadata-Version: 2.0
Name: listsave
Version: 1.2.0
Summary: A module to save and read lists to a file.
Home-page: https://github.com/novazzz/lists
Author: nova^
Author-email: bensmith8229@gmail.com
License: MIT
Keywords: lists saving
Platform: UNKNOWN
Classifier: Development Status :: 3 - Alpha
Classifier: Intended Audience :: Developers
Classifier: Topic :: Software Development :: Build Tools
Classifier: License :: OSI Approved :: MIT License
Classifier: Programming Language :: Python :: 2.7
